{"name":"bcaafced","url":"https://wg5p835kmb.coze.site","showName":"烬火社区","appid":"com.gogxian.app","icon":"","iconPath":"C:\\Users\\admin\\AppData\\Roaming\\com.pakeplus.pacbao\\1va37l2ml9h.png","iconRound":true,"state":true,"single":true,"injectJq":true,"tauriApi":false,"devbug":false,"version":"0.0.2","preview":"desktop","platform":["1-1","1-2","2-1","2-2","3-1","3-2"],"width":800,"height":600,"desc":"","jsFile":[],"filterCss":"","customJs":"// 安卓软件端加载动画脚本\n(function() {\n    // 创建加载容器\n    function createLoadingContainer() {\n        const container = document.createElement('div');\n        container.id = 'android-loading-container';\n        container.style.cssText = `\n            position: fixed;\n            top: 0;\n            left: 0;\n            width: 100%;\n            height: 100%;\n            background: rgba(255, 255, 255, 0.95);\n            display: flex;\n            flex-direction: column;\n            justify-content: center;\n            align-items: center;\n            z-index: 9999;\n            font-family: -apple-system, BlinkMacSystemFont, 'Segoe UI', Roboto, Oxygen, Ubuntu, Cantarell, sans-serif;\n        `;\n        return container;\n    }\n\n    // 创建加载动画\n    function createLoadingSpinner() {\n        const spinner = document.createElement('div');\n        spinner.id = 'android-loading-spinner';\n        spinner.style.cssText = `\n            width: 80px;\n            height: 80px;\n            border: 4px solid #f3f3f3;\n            border-top: 4px solid #3498db;\n            border-radius: 50%;\n            animation: spin 1s linear infinite, pulse 2s ease-in-out infinite;\n            margin-bottom: 30px;\n            box-shadow: 0 0 20px rgba(52, 152, 219, 0.3);\n        `;\n        return spinner;\n    }\n\n    // 创建加载文本\n    function createLoadingText() {\n        const text = document.createElement('div');\n        text.id = 'android-loading-text';\n        text.style.cssText = `\n            font-size: 20px;\n            color: #333;\n            margin-bottom: 20px;\n            font-weight: 500;\n            animation: fadeIn 1s ease-in-out;\n        `;\n        text.textContent = '系统加载中...';\n        return text;\n    }\n\n    // 创建文件加载模拟\n    function createFileLoading() {\n        const fileLoading = document.createElement('div');\n        fileLoading.id = 'android-file-loading';\n        fileLoading.style.cssText = `\n            width: 200px;\n            height: 120px;\n            background: #f8f9fa;\n            border-radius: 8px;\n            padding: 15px;\n            margin-bottom: 20px;\n            overflow-y: auto;\n            font-size: 12px;\n            color: #666;\n            box-shadow: 0 2px 10px rgba(0, 0, 0, 0.1);\n        `;\n        return fileLoading;\n    }\n\n    // 创建安卓提示\n    function createAndroidHint() {\n        const hint = document.createElement('div');\n        hint.id = 'android-hint';\n        hint.style.cssText = `\n            font-size: 14px;\n            color: #28a745;\n            font-weight: 500;\n        `;\n        hint.textContent = '当前“安卓软件端”';\n        return hint;\n    }\n\n    // 创建加载进度条\n    function createProgressBar() {\n        const progressContainer = document.createElement('div');\n        progressContainer.id = 'android-loading-progress';\n        progressContainer.style.cssText = `\n            width: 250px;\n            height: 8px;\n            background-color: #f0f0f0;\n            border-radius: 4px;\n            overflow: hidden;\n            margin-bottom: 30px;\n            box-shadow: inset 0 1px 3px rgba(0, 0, 0, 0.1);\n        `;\n\n        const progressBar = document.createElement('div');\n        progressBar.id = 'android-loading-progress-bar';\n        progressBar.style.cssText = `\n            width: 0%;\n            height: 100%;\n            background-color: #3498db;\n            border-radius: 4px;\n            animation: progress 3s ease-in-out forwards;\n            background-image: linear-gradient(90deg, #3498db, #2ecc71);\n        `;\n\n        progressContainer.appendChild(progressBar);\n        return progressContainer;\n    }\n\n    // 添加动画样式\n    function addAnimationStyles() {\n        const style = document.createElement('style');\n        style.textContent = `\n            @keyframes spin {\n                0% { transform: rotate(0deg); }\n                100% { transform: rotate(360deg); }\n            }\n            @keyframes pulse {\n                0% { box-shadow: 0 0 20px rgba(52, 152, 219, 0.3); }\n                50% { box-shadow: 0 0 40px rgba(52, 152, 219, 0.6); }\n                100% { box-shadow: 0 0 20px rgba(52, 152, 219, 0.3); }\n            }\n            @keyframes fadeIn {\n                0% { opacity: 0; transform: translateY(-10px); }\n                100% { opacity: 1; transform: translateY(0); }\n            }\n            @keyframes progress {\n                0% { width: 0%; }\n                100% { width: 100%; }\n            }\n        `;\n        document.head.appendChild(style);\n    }\n\n    // 创建可拖动的跳转按钮\n    function createDraggableButton() {\n        const button = document.createElement('div');\n        button.id = 'android-home-button';\n        button.style.cssText = `\n            position: fixed;\n            bottom: 20px;\n            right: 20px;\n            width: 60px;\n            height: 60px;\n            background-color: #3498db;\n            color: white;\n            border-radius: 50%;\n            display: flex;\n            justify-content: center;\n            align-items: center;\n            cursor: move;\n            z-index: 9998;\n            box-shadow: 0 2px 10px rgba(0, 0, 0, 0.2);\n            font-size: 12px;\n            text-align: center;\n            padding: 10px;\n            box-sizing: border-box;\n            transition: background-color 0.3s;\n        `;\n        button.textContent = '首页';\n        button.title = '点击跳转到首页';\n\n        // 添加点击跳转功能\n        button.addEventListener('click', function(e) {\n            e.stopPropagation();\n            window.location.href = 'https://wg5p835kmb.coze.site/store';\n        });\n\n        // 添加拖动功能\n        let isDragging = false;\n        let offsetX, offsetY;\n\n        button.addEventListener('mousedown', function(e) {\n            isDragging = true;\n            offsetX = e.clientX - button.getBoundingClientRect().left;\n            offsetY = e.clientY - button.getBoundingClientRect().top;\n            button.style.zIndex = '9999';\n        });\n\n        document.addEventListener('mousemove', function(e) {\n            if (isDragging) {\n                const x = e.clientX - offsetX;\n                const y = e.clientY - offsetY;\n                button.style.left = x + 'px';\n                button.style.top = y + 'px';\n                button.style.bottom = 'auto';\n                button.style.right = 'auto';\n            }\n        });\n\n        document.addEventListener('mouseup', function() {\n            if (isDragging) {\n                isDragging = false;\n                button.style.zIndex = '9998';\n            }\n        });\n\n        // 触摸设备支持\n        button.addEventListener('touchstart', function(e) {\n            isDragging = true;\n            const touch = e.touches[0];\n            offsetX = touch.clientX - button.getBoundingClientRect().left;\n            offsetY = touch.clientY - button.getBoundingClientRect().top;\n            button.style.zIndex = '9999';\n            e.preventDefault();\n        });\n\n        document.addEventListener('touchmove', function(e) {\n            if (isDragging) {\n                const touch = e.touches[0];\n                const x = touch.clientX - offsetX;\n                const y = touch.clientY - offsetY;\n                button.style.left = x + 'px';\n                button.style.top = y + 'px';\n                button.style.bottom = 'auto';\n                button.style.right = 'auto';\n                e.preventDefault();\n            }\n        });\n\n        document.addEventListener('touchend', function() {\n            if (isDragging) {\n                isDragging = false;\n                button.style.zIndex = '9998';\n            }\n        });\n\n        return button;\n    }\n\n    // 模拟文件加载\n    function simulateFileLoading(fileLoadingElement) {\n        const files = [\n            'config.json',\n            'userdata.dat',\n            'appsettings.xml',\n            'resources/assets.bin',\n            'database/local.db',\n            'cache/temp.tmp'\n        ];\n\n        let index = 0;\n        const interval = setInterval(() => {\n            if (index < files.length) {\n                const fileItem = document.createElement('div');\n                fileItem.style.cssText = `\n                    margin-bottom: 5px;\n                    display: flex;\n                    align-items: center;\n                `;\n                fileItem.innerHTML = `<span style=\"color: #3498db;\">✓</span> <span style=\"margin-left: 8px;\">${files[index]}</span>`;\n                fileLoadingElement.appendChild(fileItem);\n                index++;\n            } else {\n                clearInterval(interval);\n                // 加载完成后移除加载界面并添加跳转按钮\n                setTimeout(() => {\n                    const container = document.getElementById('android-loading-container');\n                    if (container) {\n                        container.style.opacity = '0';\n                        container.style.transition = 'opacity 0.5s ease';\n                        setTimeout(() => {\n                            container.remove();\n                            // 添加可拖动的跳转按钮\n                            const button = createDraggableButton();\n                            document.body.appendChild(button);\n                        }, 500);\n                    }\n                }, 1000);\n            }\n        }, 500);\n    }\n\n    // 初始化加载界面\n    function initLoading() {\n        // 检查是否已存在加载界面\n        if (document.getElementById('android-loading-container')) {\n            return;\n        }\n\n        // 添加动画样式\n        addAnimationStyles();\n\n        // 创建加载容器\n        const container = createLoadingContainer();\n\n        // 创建并添加加载动画\n        const spinner = createLoadingSpinner();\n        container.appendChild(spinner);\n\n        // 创建并添加加载文本\n        const text = createLoadingText();\n        container.appendChild(text);\n\n        // 创建并添加加载进度条\n        const progressBar = createProgressBar();\n        container.appendChild(progressBar);\n\n        // 创建并添加文件加载模拟\n        const fileLoading = createFileLoading();\n        container.appendChild(fileLoading);\n\n        // 创建并添加安卓提示\n        const hint = createAndroidHint();\n        container.appendChild(hint);\n\n        // 添加到文档\n        document.body.appendChild(container);\n\n        // 开始模拟文件加载\n        simulateFileLoading(fileLoading);\n    }\n\n    // 页面加载完成后初始化\n    if (document.readyState === 'loading') {\n        document.addEventListener('DOMContentLoaded', initLoading);\n    } else {\n        initLoading();\n    }\n})();","isHtml":false,"htmlPath":"","htmlFiles":[],"prefix":"","pcRepo":"PakePlus-v2.1.7","iosRepo":"PakePlus-iOS-v2.1.7","androidRepo":"PakePlus-Android-v2.1.7","more":{"windows":{"label":"","title":"烬火社区","url":"https://wg5p835kmb.coze.site","userAgent":"Mozilla/5.0 (Macintosh; Intel Mac OS X 10_15_7) AppleWebKit/537.36 (KHTML, like Gecko) Chrome/130.0.0.0 Safari/537.36","width":800,"height":600,"theme":null,"resizable":true,"fullscreen":false,"maximized":false,"minWidth":400,"minHeight":300,"maxWidth":1920,"maxHeight":1080,"decorations":true,"transparent":false,"titleBarStyle":"Visible","visible":true,"focus":true,"closable":true,"minimizable":true,"maximizable":true,"alwaysOnTop":false,"alwaysOnBottom":false,"center":false,"shadow":true,"skipTaskbar":false,"tabbingIdentifier":null,"parent":null,"dragDropEnabled":true,"browserExtensionsEnabled":false,"devtools":true,"contentProtected":false,"hiddenTitle":false,"incognito":false,"proxyUrl":null,"useHttpsScheme":false,"zoomHotkeysEnabled":false,"acceptFirstMouse":false,"create":false,"backgroundColor":null,"backgroundThrottling":null,"javascriptDisabled":false}},"phone":{"fullScreen":false,"safeArea":{"top":0,"bottom":0,"left":0,"right":0},"header":{"show":false,"title":"","backgroundColor":"","color":"","fontSize":16,"fontWeight":"bold","loading":false,"toolBar":false,"toolBarBackgroundColor":"","toolBarColor":"","toolBarFontSize":16,"toolBarFontWeight":"bold"},"siderMenu":{"show":false,"width":0,"backgroundColor":"","color":"","fontSize":16,"fontWeight":"bold","title":"","titleColor":"","titleFontSize":16,"titleFontWeight":"bold"},"tabBar":{"show":false,"backgroundColor":"","color":"","activeColor":"","fontSize":16,"fontWeight":"bold","tabBarItem":[]},"webview":{"userAgent":"","javaScriptEnabled":true,"domStorageEnabled":true,"allowFileAccess":true,"loadWithOverviewMode":true,"setSupportZoom":true,"clearCache":true}},"ios":{"name":"bcaafced","showName":"烬火社区","version":"0.0.2","webUrl":"https://wg5p835kmb.coze.site","id":"com.gogxian.app.ios","icon":"./app-icon.png","desc":"Package for personal use only, please do not use for commercial purposes（打包仅限个人使用，请勿传播或商业用途）","pubBody":"Package for personal use only, please do not use for commercial purposes（打包仅限个人使用，请勿传播或商业用途）","isHtml":false,"debug":false,"safeArea":"all"},"android":{"name":"bcaafced","showName":"烬火社区","version":"0.0.2","webUrl":"https://wg5p835kmb.coze.site","id":"com.gogxian.app.android","icon":"./app-icon.png","input":"./app-icon.png","output":"./res","rounded":true,"copyTo":"./app/src/main/res","androidResDir":"./app/src/main/res","desc":"Package for personal use only, please do not use for commercial purposes（打包仅限个人使用，请勿传播或商业用途）","pubBody":"Package for personal use only, please do not use for commercial purposes（打包仅限个人使用，请勿传播或商业用途）","isHtml":false,"debug":false,"safeArea":"all"},"desktop":{"name":"bcaafced","showName":"烬火社区","version":"0.0.2","id":"com.gogxian.app.desktop","desc":"打包仅限个人使用，请勿传播或商业用途，否则后果自负","webUrl":"https://wg5p835kmb.coze.site","iconPath":"../app-icon.png","inputPath":"../app-icon.png","tempPath":"./processed-image.png","icnsPath":"../src-tauri/icons/icon.icns","pubBody":"打包仅限个人使用，请勿传播或商业用途，否则后果自负","isHtml":false,"single":true,"state":true,"injectJq":false,"tauriApi":false,"buildMethod":"cloud","debug":false}}